execy/__init__.py
execy/exec.py
execy-0.1.9.dist-info/METADATA
execy-0.1.9.dist-info/WHEEL
execy-0.1.9.dist-info/licenses/LICENSE
execy-0.1.9.dist-info/RECORD
