Metadata-Version: 2.1
Name: execy
Version: 0.1.9
Summary: The ececy exec_time decorator is a utility that measures the execution time of a function. It can be used to easily track and log the time taken by a function to execute, both for synchronous and asynchronous functions.
Author-email: hglong16 <intihad.vuong@gmail.com>
License-File: LICENSE
Requires-Python: >=3.8
